README.md
setup.py
half_json/__init__.py
half_json/core.py
half_json/json_util.py
half_json/main.py
halfjson.egg-info/PKG-INFO
halfjson.egg-info/SOURCES.txt
halfjson.egg-info/dependency_links.txt
halfjson.egg-info/entry_points.txt
halfjson.egg-info/top_level.txt