Metadata-Version: 1.1
Name: halfjson
Version: 0.1.2
Summary: A command tool/package fix invalid json: broken-json / truncated-json.
Home-page: https://github.com/half-pie/half-json
Author: alingse
Author-email: alingse@foxmail.com
License: UNKNOWN
Platform: UNKNOWN
Classifier: License :: OSI Approved :: MIT License
Classifier: Operating System :: OS Independent
Classifier: Programming Language :: Python
Classifier: Programming Language :: Python :: 2.7
